pytest_dir_equal-0.2.1.dist-info/METADATA
pytest_dir_equal-0.2.1.dist-info/WHEEL
pytest_dir_equal-0.2.1.dist-info/entry_points.txt
pytest_dir_equal-0.2.1.dist-info/licenses/LICENSE
pytest_dir_equal/.gitignore
pytest_dir_equal/VERSION
pytest_dir_equal/__init__.py
pytest_dir_equal/plugin.py
pytest_dir_equal/py.typed
pytest_dir_equal-0.2.1.dist-info/RECORD
