Metadata-Version: 2.1
Name: pytest-dir-equal
Version: 0.2.1
Summary: pytest-dir-equals is a pytest plugin providing helpers to assert directories equality allowing golden testing
Author-Email: Axel Haustant <noirbizarre@gmail.com>
License: MIT
Classifier: Development Status :: 4 - Beta
Classifier: Intended Audience :: Developers
Classifier: Programming Language :: Python
Classifier: Programming Language :: Python :: 3
Classifier: Programming Language :: Python :: 3 :: Only
Classifier: Programming Language :: Python :: 3.8
Classifier: Programming Language :: Python :: 3.9
Classifier: Programming Language :: Python :: 3.10
Classifier: Programming Language :: Python :: 3.11
Classifier: Programming Language :: Python :: 3.12
Classifier: Typing :: Typed
Project-URL: Homepage, https://github.com/noirbizarre/pytest-dir-equal
Project-URL: Documentation, https://github.com/noirbizarre/pytest-dir-equal#readme
Project-URL: Repository, https://github.com/noirbizarre/pytest-dir-equal
Project-URL: Issues, https://github.com/noirbizarre/pytest-dir-equal/issues
Requires-Python: >=3.8
Requires-Dist: pytest>=7.3.2
Requires-Dist: icdiff>=2.0.6
